COPYING.LESSER
MANIFEST.in
README.rst
setup.cfg
setup.py
tox.ini
simulagora/__init__.py
simulagora/__main__.py
simulagora.egg-info/PKG-INFO
simulagora.egg-info/SOURCES.txt
simulagora.egg-info/dependency_links.txt
simulagora.egg-info/entry_points.txt
simulagora.egg-info/requires.txt
simulagora.egg-info/top_level.txt