Metadata-Version: 1.1
Name: simulagora
Version: 0.3.0
Summary: A python library to use Simulagora programatically
Home-page: http://www.cubicweb.org/project/simulagora-client
Author: LOGILAB S.A. (Paris, FRANCE)
Author-email: contact@logilab.fr
License: UNKNOWN
Keywords: simulagora cubicweb cwclientlib
Platform: UNKNOWN
Classifier: Environment :: Console
Classifier: Intended Audience :: Science/Research
Classifier: Programming Language :: Python
Classifier: Topic :: Scientific/Engineering
